agnets/__init__.py
agnets/agent.py
agnets/agentv2.py
agnets/config.py
agnets/fleet.py
agnets/utils.py
agnets/backends/litellm.py
agnets/backends/ollama.py
agnets/backends/openai.py
agnets/types/backend.py
agnets/types/literals.py
agnets/types/message.py
agnets-0.4.0.dist-info/METADATA
agnets-0.4.0.dist-info/WHEEL
agnets-0.4.0.dist-info/licenses/LICENSE.md
agnets-0.4.0.dist-info/RECORD
