Metadata-Version: 2.4
Name: agnets
Version: 0.4.0
Summary: A multi-agentic python framework.
License-File: LICENSE.md
Requires-Python: >=3.12
Requires-Dist: asyncio>=4.0.0
Requires-Dist: litellm>=1.75.5.post1
Requires-Dist: mcp>=1.12.0
Requires-Dist: pydantic>=2.11.7
Provides-Extra: ollama
Requires-Dist: ollama>=0.5.1; extra == 'ollama'
Provides-Extra: openai
Requires-Dist: openai>=1.98.0; extra == 'openai'
